mwtoolbox/__init__.py
mwtoolbox/components.py
mwtoolbox/filters.py
mwtoolbox/genel.py
mwtoolbox/myconstants.py
mwtoolbox/network.py
mwtoolbox/networksym.py
mwtoolbox/plots.py
mwtoolbox/rfnetwork.py
mwtoolbox/smithplot.py
mwtoolbox/transmission_lines.py
mwtoolbox/vectfit3.py
mwtoolbox/em/__init__.py
mwtoolbox/em/fdfd_2d/__init__.py
mwtoolbox/em/fdfd_2d/fdfd_2d.py
mwtoolbox/em/fdfd_2d/grid3.py
mwtoolbox/em/mode_matching/__init__.py
mwtoolbox/em/mode_matching/mode_matching_module.py
mwtoolbox-0.0.12.dist-info/licenses/LICENSE
mwtoolbox-0.0.12.dist-info/METADATA
mwtoolbox-0.0.12.dist-info/WHEEL
mwtoolbox-0.0.12.dist-info/top_level.txt
mwtoolbox-0.0.12.dist-info/RECORD
