Metadata-Version: 2.4
Name: mwtoolbox
Version: 0.0.12
Summary: Microwave Toolbox
Author-email: Tuncay Erdöl <terdol@hotmail.com>
License: MIT
Keywords: microwave,rf,s-parameters
Classifier: Development Status :: 3 - Alpha
Classifier: License :: OSI Approved :: MIT License
Classifier: Operating System :: OS Independent
Classifier: Programming Language :: Python :: 3.8
Classifier: Topic :: Scientific/Engineering
Requires-Python: >=3.10
License-File: LICENSE
Requires-Dist: quantities
Requires-Dist: numpy
Requires-Dist: scipy
Requires-Dist: sympy
Dynamic: license-file
